{
  "summary": [
    {
      "Coef.": "-2.549",
      "Std.Err.": "0.368",
      "z": "-6.933",
      "P>|z|": "0.000",
      "[0.025": "-3.270",
      "0.975]": "-1.829"
    },
    {
      "Coef.": "-0.897",
      "Std.Err.": "0.339",
      "z": "-2.641",
      "P>|z|": "0.008",
      "[0.025": "-1.562",
      "0.975]": "-0.231"
    },
    {
      "Coef.": "1.630",
      "Std.Err.": "0.918",
      "z": "",
      "P>|z|": "",
      "[0.025": "",
      "0.975]": ""
    }
  ],
  "aic": 166.06582879548947,
  "bic": 173.1106292582637,
  "converged": true
}