{
  "summary": [
    {
      "Coef.": "177.780",
      "Std.Err.": "2.834",
      "z": "62.731",
      "P>|z|": "0.000",
      "[0.025": "172.225",
      "0.975]": "183.334"
    },
    {
      "Coef.": "-2.439",
      "Std.Err.": "3.123",
      "z": "-0.781",
      "P>|z|": "0.435",
      "[0.025": "-8.560",
      "0.975]": "3.683"
    },
    {
      "Coef.": "-1.996",
      "Std.Err.": "3.133",
      "z": "-0.637",
      "P>|z|": "0.524",
      "[0.025": "-8.137",
      "0.975]": "4.145"
    },
    {
      "Coef.": "46.280",
      "Std.Err.": "3.244",
      "z": "",
      "P>|z|": "",
      "[0.025": "",
      "0.975]": ""
    }
  ],
  "aic": 465.94950677417467,
  "bic": 476.4212295852852,
  "converged": true
}