{
  "summary": [
    {
      "Coef.": "461.410",
      "Std.Err.": "8.271",
      "z": "55.785",
      "P>|z|": "0.000",
      "[0.025": "445.199",
      "0.975]": "477.622"
    },
    {
      "Coef.": "4.281",
      "Std.Err.": "8.179",
      "z": "0.523",
      "P>|z|": "0.601",
      "[0.025": "-11.750",
      "0.975]": "20.312"
    },
    {
      "Coef.": "-0.017",
      "Std.Err.": "1.376",
      "z": "-0.013",
      "P>|z|": "0.990",
      "[0.025": "-2.715",
      "0.975]": "2.680"
    },
    {
      "Coef.": "0.000",
      "Std.Err.": "6.332",
      "z": "",
      "P>|z|": "",
      "[0.025": "",
      "0.975]": ""
    }
  ],
  "aic": 341.83563623924294,
  "bic": 349.7532309315235,
  "converged": true
}