{
  "summary": [
    {
      "Coef.": "474.200",
      "Std.Err.": "10.289",
      "z": "46.088",
      "P>|z|": "0.000",
      "[0.025": "454.034",
      "0.975]": "494.366"
    },
    {
      "Coef.": "-27.700",
      "Std.Err.": "15.372",
      "z": "-1.802",
      "P>|z|": "0.072",
      "[0.025": "-57.828",
      "0.975]": "2.428"
    },
    {
      "Coef.": "0.000",
      "Std.Err.": "13.010",
      "z": "",
      "P>|z|": "",
      "[0.025": "",
      "0.975]": ""
    }
  ],
  "aic": 385.4739469971081,
  "bic": 391.80802275093254,
  "converged": true
}