{
  "summary": [
    {
      "name": "Intercept",
      "Coef.": "177.091",
      "Std.Err.": "3.160",
      "z": "56.033",
      "P>|z|": "0.000",
      "[0.025": "170.896",
      "0.975]": "183.285"
    },
    {
      "name": "condition[T.1b]",
      "Coef.": "-1.787",
      "Std.Err.": "3.600",
      "z": "-0.496",
      "P>|z|": "0.620",
      "[0.025": "-8.843",
      "0.975]": "5.268"
    },
    {
      "name": "condition[T.1c]",
      "Coef.": "-1.087",
      "Std.Err.": "3.465",
      "z": "-0.314",
      "P>|z|": "0.754",
      "[0.025": "-7.879",
      "0.975]": "5.705"
    },
    {
      "name": "condition[T.1d]",
      "Coef.": "4.168",
      "Std.Err.": "3.416",
      "z": "1.220",
      "P>|z|": "0.222",
      "[0.025": "-2.528",
      "0.975]": "10.864"
    },
    {
      "name": "snr",
      "Coef.": "0.794",
      "Std.Err.": "0.755",
      "z": "1.051",
      "P>|z|": "0.293",
      "[0.025": "-0.687",
      "0.975]": "2.275"
    },
    {
      "name": "Group Var",
      "Coef.": "30.044",
      "Std.Err.": "2.801",
      "z": "",
      "P>|z|": "",
      "[0.025": "",
      "0.975]": ""
    }
  ],
  "aic": 421.81061345817477,
  "bic": 435.98807529332083,
  "converged": true,
  "reference_condition": "1a"
}