{
  "summary": [
    {
      "Coef.": "492.465",
      "Std.Err.": "5.594",
      "z": "88.039",
      "P>|z|": "0.000",
      "[0.025": "481.502",
      "0.975]": "503.429"
    },
    {
      "Coef.": "8.226",
      "Std.Err.": "4.208",
      "z": "1.955",
      "P>|z|": "0.051",
      "[0.025": "-0.021",
      "0.975]": "16.474"
    },
    {
      "Coef.": "-0.015",
      "Std.Err.": "0.593",
      "z": "-0.024",
      "P>|z|": "0.980",
      "[0.025": "-1.177",
      "0.975]": "1.148"
    },
    {
      "Coef.": "121.597",
      "Std.Err.": "14.317",
      "z": "",
      "P>|z|": "",
      "[0.025": "",
      "0.975]": ""
    }
  ],
  "aic": 223.00182881939517,
  "bic": 229.4810131494168,
  "converged": true
}