{
  "summary": [
    {
      "name": "Intercept",
      "Coef.": "-0.896",
      "Std.Err.": "0.422",
      "z": "-2.123",
      "P>|z|": "0.034",
      "[0.025": "-1.724",
      "0.975]": "-0.069"
    },
    {
      "name": "condition[T.Increasing Large (no 1)]",
      "Coef.": "-0.623",
      "Std.Err.": "0.468",
      "z": "-1.332",
      "P>|z|": "0.183",
      "[0.025": "-1.540",
      "0.975]": "0.294"
    },
    {
      "name": "condition[T.Increasing Small (no 1)]",
      "Coef.": "-0.155",
      "Std.Err.": "0.468",
      "z": "-0.331",
      "P>|z|": "0.741",
      "[0.025": "-1.072",
      "0.975]": "0.762"
    },
    {
      "name": "snr",
      "Coef.": "-0.268",
      "Std.Err.": "0.151",
      "z": "-1.779",
      "P>|z|": "0.075",
      "[0.025": "-0.564",
      "0.975]": "0.027"
    },
    {
      "name": "Group Var",
      "Coef.": "0.288",
      "Std.Err.": "0.255",
      "z": "",
      "P>|z|": "",
      "[0.025": "",
      "0.975]": ""
    }
  ],
  "aic": 292.69559320191235,
  "bic": 306.3555899160087,
  "converged": true,
  "reference_condition": "Increasing Crossover (no 1)"
}