{
  "summary": [
    {
      "name": "Intercept",
      "Coef.": "-3.535",
      "Std.Err.": "0.459",
      "z": "-7.694",
      "P>|z|": "0.000",
      "[0.025": "-4.435",
      "0.975]": "-2.634"
    },
    {
      "name": "condition[T.Decreasing 3 to 1]",
      "Coef.": "0.196",
      "Std.Err.": "0.448",
      "z": "0.438",
      "P>|z|": "0.661",
      "[0.025": "-0.681",
      "0.975]": "1.073"
    },
    {
      "name": "condition[T.Increasing 1 to 2]",
      "Coef.": "-0.409",
      "Std.Err.": "0.459",
      "z": "-0.892",
      "P>|z|": "0.372",
      "[0.025": "-1.308",
      "0.975]": "0.490"
    },
    {
      "name": "condition[T.Increasing 1 to 3]",
      "Coef.": "-0.697",
      "Std.Err.": "0.484",
      "z": "-1.439",
      "P>|z|": "0.150",
      "[0.025": "-1.646",
      "0.975]": "0.252"
    },
    {
      "name": "snr",
      "Coef.": "-0.421",
      "Std.Err.": "0.064",
      "z": "-6.549",
      "P>|z|": "0.000",
      "[0.025": "-0.547",
      "0.975]": "-0.295"
    },
    {
      "name": "Group Var",
      "Coef.": "1.806",
      "Std.Err.": "0.620",
      "z": "",
      "P>|z|": "",
      "[0.025": "",
      "0.975]": ""
    }
  ],
  "aic": 326.1285808887059,
  "bic": 342.9756156195557,
  "converged": true,
  "reference_condition": "Decreasing 2 to 1"
}