{
  "summary": [
    {
      "name": "Intercept",
      "Coef.": "119.229",
      "Std.Err.": "3.936",
      "z": "30.290",
      "P>|z|": "0.000",
      "[0.025": "111.514",
      "0.975]": "126.944"
    },
    {
      "name": "condition[T.2 to 1]",
      "Coef.": "-1.983",
      "Std.Err.": "4.693",
      "z": "-0.423",
      "P>|z|": "0.673",
      "[0.025": "-11.181",
      "0.975]": "7.215"
    },
    {
      "name": "condition[T.3 to 1]",
      "Coef.": "-2.916",
      "Std.Err.": "4.988",
      "z": "-0.585",
      "P>|z|": "0.559",
      "[0.025": "-12.693",
      "0.975]": "6.860"
    },
    {
      "name": "condition[T.4 to 1]",
      "Coef.": "-0.464",
      "Std.Err.": "4.750",
      "z": "-0.098",
      "P>|z|": "0.922",
      "[0.025": "-9.774",
      "0.975]": "8.846"
    },
    {
      "name": "snr",
      "Coef.": "0.307",
      "Std.Err.": "1.230",
      "z": "0.249",
      "P>|z|": "0.803",
      "[0.025": "-2.104",
      "0.975]": "2.717"
    },
    {
      "name": "Group Var",
      "Coef.": "3.652",
      "Std.Err.": "1.836",
      "z": "",
      "P>|z|": "",
      "[0.025": "",
      "0.975]": ""
    }
  ],
  "aic": 529.0569666347942,
  "bic": 544.1691482183119,
  "converged": true,
  "reference_condition": "1 to 1"
}