{
  "summary": [
    {
      "Coef.": "-0.619",
      "Std.Err.": "0.399",
      "z": "-1.551",
      "P>|z|": "0.121",
      "[0.025": "-1.400",
      "0.975]": "0.163"
    },
    {
      "Coef.": "-0.868",
      "Std.Err.": "0.400",
      "z": "-2.170",
      "P>|z|": "0.030",
      "[0.025": "-1.653",
      "0.975]": "-0.084"
    },
    {
      "Coef.": "-1.220",
      "Std.Err.": "0.385",
      "z": "-3.167",
      "P>|z|": "0.002",
      "[0.025": "-1.975",
      "0.975]": "-0.465"
    },
    {
      "Coef.": "-0.348",
      "Std.Err.": "0.385",
      "z": "-0.905",
      "P>|z|": "0.366",
      "[0.025": "-1.103",
      "0.975]": "0.406"
    },
    {
      "Coef.": "-0.478",
      "Std.Err.": "0.050",
      "z": "-9.647",
      "P>|z|": "0.000",
      "[0.025": "-0.575",
      "0.975]": "-0.381"
    },
    {
      "Coef.": "0.957",
      "Std.Err.": "0.421",
      "z": "",
      "P>|z|": "",
      "[0.025": "",
      "0.975]": ""
    }
  ],
  "aic": 268.02951955297283,
  "bic": 284.157975205402,
  "converged": true
}