{
  "summary": [
    {
      "name": "Intercept",
      "Coef.": "484.040",
      "Std.Err.": "7.914",
      "z": "61.159",
      "P>|z|": "0.000",
      "[0.025": "468.528",
      "0.975]": "499.552"
    },
    {
      "name": "condition[T.Decreasing Large]",
      "Coef.": "8.313",
      "Std.Err.": "7.128",
      "z": "1.166",
      "P>|z|": "0.244",
      "[0.025": "-5.658",
      "0.975]": "22.284"
    },
    {
      "name": "condition[T.Decreasing Small]",
      "Coef.": "3.240",
      "Std.Err.": "6.881",
      "z": "0.471",
      "P>|z|": "0.638",
      "[0.025": "-10.247",
      "0.975]": "16.728"
    },
    {
      "name": "snr",
      "Coef.": "-0.764",
      "Std.Err.": "0.492",
      "z": "-1.552",
      "P>|z|": "0.121",
      "[0.025": "-1.729",
      "0.975]": "0.201"
    },
    {
      "name": "Group Var",
      "Coef.": "396.412",
      "Std.Err.": "9.055",
      "z": "",
      "P>|z|": "",
      "[0.025": "",
      "0.975]": ""
    }
  ],
  "aic": 694.664185852316,
  "bic": 708.3241825664123,
  "converged": true,
  "reference_condition": "Decreasing Crossover"
}