{
  "summary": [
    {
      "name": "Intercept",
      "Coef.": "104.017",
      "Std.Err.": "2.235",
      "z": "46.532",
      "P>|z|": "0.000",
      "[0.025": "99.635",
      "0.975]": "108.398"
    },
    {
      "name": "condition[T.2 to 4]",
      "Coef.": "-0.279",
      "Std.Err.": "2.425",
      "z": "-0.115",
      "P>|z|": "0.908",
      "[0.025": "-5.032",
      "0.975]": "4.473"
    },
    {
      "name": "condition[T.3 to 4]",
      "Coef.": "3.000",
      "Std.Err.": "2.380",
      "z": "1.260",
      "P>|z|": "0.208",
      "[0.025": "-1.665",
      "0.975]": "7.665"
    },
    {
      "name": "condition[T.5 to 4]",
      "Coef.": "0.867",
      "Std.Err.": "2.417",
      "z": "0.359",
      "P>|z|": "0.720",
      "[0.025": "-3.871",
      "0.975]": "5.605"
    },
    {
      "name": "condition[T.6 to 4]",
      "Coef.": "2.496",
      "Std.Err.": "2.332",
      "z": "1.070",
      "P>|z|": "0.284",
      "[0.025": "-2.074",
      "0.975]": "7.067"
    },
    {
      "name": "condition[T.Cardinality4]",
      "Coef.": "0.424",
      "Std.Err.": "2.458",
      "z": "0.172",
      "P>|z|": "0.863",
      "[0.025": "-4.393",
      "0.975]": "5.240"
    },
    {
      "name": "snr",
      "Coef.": "1.023",
      "Std.Err.": "0.574",
      "z": "1.782",
      "P>|z|": "0.075",
      "[0.025": "-0.102",
      "0.975]": "2.149"
    },
    {
      "name": "Group Var",
      "Coef.": "16.306",
      "Std.Err.": "1.463",
      "z": "",
      "P>|z|": "",
      "[0.025": "",
      "0.975]": ""
    }
  ],
  "aic": 643.3722680892874,
  "bic": 666.1656635276668,
  "converged": true,
  "reference_condition": "1 to 4"
}