{
  "summary": [
    {
      "name": "Intercept",
      "Coef.": "463.695",
      "Std.Err.": "6.784",
      "z": "68.353",
      "P>|z|": "0.000",
      "[0.025": "450.399",
      "0.975]": "476.991"
    },
    {
      "name": "condition[T.2 to 4]",
      "Coef.": "9.749",
      "Std.Err.": "7.733",
      "z": "1.261",
      "P>|z|": "0.207",
      "[0.025": "-5.408",
      "0.975]": "24.906"
    },
    {
      "name": "condition[T.3 to 5]",
      "Coef.": "-0.095",
      "Std.Err.": "8.210",
      "z": "-0.012",
      "P>|z|": "0.991",
      "[0.025": "-16.187",
      "0.975]": "15.996"
    },
    {
      "name": "condition[T.4 to 6]",
      "Coef.": "7.619",
      "Std.Err.": "7.839",
      "z": "0.972",
      "P>|z|": "0.331",
      "[0.025": "-7.744",
      "0.975]": "22.983"
    },
    {
      "name": "snr",
      "Coef.": "-0.534",
      "Std.Err.": "0.953",
      "z": "-0.561",
      "P>|z|": "0.575",
      "[0.025": "-2.402",
      "0.975]": "1.334"
    },
    {
      "name": "Group Var",
      "Coef.": "0.000",
      "Std.Err.": "2.933",
      "z": "",
      "P>|z|": "",
      "[0.025": "",
      "0.975]": ""
    }
  ],
  "aic": 685.7746855221098,
  "bic": 701.8079016101486,
  "converged": true,
  "reference_condition": "1 to 3"
}