{
  "summary": [
    {
      "Coef.": "4.125",
      "Std.Err.": "0.512",
      "z": "8.060",
      "P>|z|": "0.000",
      "[0.025": "3.122",
      "0.975]": "5.128"
    },
    {
      "Coef.": "-0.397",
      "Std.Err.": "0.672",
      "z": "-0.591",
      "P>|z|": "0.555",
      "[0.025": "-1.715",
      "0.975]": "0.921"
    },
    {
      "Coef.": "-0.085",
      "Std.Err.": "0.684",
      "z": "-0.124",
      "P>|z|": "0.901",
      "[0.025": "-1.426",
      "0.975]": "1.256"
    },
    {
      "Coef.": "-0.660",
      "Std.Err.": "0.661",
      "z": "-0.997",
      "P>|z|": "0.319",
      "[0.025": "-1.956",
      "0.975]": "0.637"
    },
    {
      "Coef.": "1.036",
      "Std.Err.": "0.397",
      "z": "",
      "P>|z|": "",
      "[0.025": "",
      "0.975]": ""
    }
  ],
  "aic": 341.3701589015981,
  "bic": 355.1945494608231,
  "converged": true
}