{
  "summary": [
    {
      "Coef.": "110.035",
      "Std.Err.": "1.375",
      "z": "80.046",
      "P>|z|": "0.000",
      "[0.025": "107.340",
      "0.975]": "112.729"
    },
    {
      "Coef.": "1.587",
      "Std.Err.": "1.892",
      "z": "0.839",
      "P>|z|": "0.402",
      "[0.025": "-2.122",
      "0.975]": "5.296"
    },
    {
      "Coef.": "0.702",
      "Std.Err.": "1.522",
      "z": "0.461",
      "P>|z|": "0.645",
      "[0.025": "-2.280",
      "0.975]": "3.684"
    },
    {
      "Coef.": "1.249",
      "Std.Err.": "1.727",
      "z": "0.723",
      "P>|z|": "0.470",
      "[0.025": "-2.135",
      "0.975]": "4.633"
    },
    {
      "Coef.": "1.553",
      "Std.Err.": "1.723",
      "z": "0.902",
      "P>|z|": "0.367",
      "[0.025": "-1.823",
      "0.975]": "4.930"
    },
    {
      "Coef.": "2.877",
      "Std.Err.": "1.088",
      "z": "",
      "P>|z|": "",
      "[0.025": "",
      "0.975]": ""
    }
  ],
  "aic": 192.11039697472467,
  "bic": 202.99783340515057,
  "converged": true
}