{
  "summary": [
    {
      "name": "Intercept",
      "Coef.": "-2.762",
      "Std.Err.": "0.316",
      "z": "-8.728",
      "P>|z|": "0.000",
      "[0.025": "-3.382",
      "0.975]": "-2.142"
    },
    {
      "name": "condition[T.b]",
      "Coef.": "0.023",
      "Std.Err.": "0.222",
      "z": "0.103",
      "P>|z|": "0.918",
      "[0.025": "-0.413",
      "0.975]": "0.458"
    },
    {
      "name": "condition[T.c]",
      "Coef.": "0.485",
      "Std.Err.": "0.220",
      "z": "2.210",
      "P>|z|": "0.027",
      "[0.025": "0.055",
      "0.975]": "0.916"
    },
    {
      "name": "condition[T.d]",
      "Coef.": "0.047",
      "Std.Err.": "0.218",
      "z": "0.214",
      "P>|z|": "0.830",
      "[0.025": "-0.380",
      "0.975]": "0.473"
    },
    {
      "name": "condition[T.e]",
      "Coef.": "-0.153",
      "Std.Err.": "0.227",
      "z": "-0.675",
      "P>|z|": "0.499",
      "[0.025": "-0.597",
      "0.975]": "0.291"
    },
    {
      "name": "snr",
      "Coef.": "-0.088",
      "Std.Err.": "0.018",
      "z": "-4.990",
      "P>|z|": "0.000",
      "[0.025": "-0.122",
      "0.975]": "-0.053"
    },
    {
      "name": "Group Var",
      "Coef.": "1.500",
      "Std.Err.": "0.738",
      "z": "",
      "P>|z|": "",
      "[0.025": "",
      "0.975]": ""
    }
  ],
  "aic": 346.3167217270483,
  "bic": 368.4821987227736,
  "converged": true,
  "reference_condition": "a"
}