{
  "summary": [
    {
      "name": "Intercept",
      "Coef.": "-1.056",
      "Std.Err.": "0.248",
      "z": "-4.254",
      "P>|z|": "0.000",
      "[0.025": "-1.543",
      "0.975]": "-0.570"
    },
    {
      "name": "condition[T.b]",
      "Coef.": "-0.008",
      "Std.Err.": "0.188",
      "z": "-0.044",
      "P>|z|": "0.965",
      "[0.025": "-0.378",
      "0.975]": "0.361"
    },
    {
      "name": "condition[T.c]",
      "Coef.": "-0.013",
      "Std.Err.": "0.190",
      "z": "-0.069",
      "P>|z|": "0.945",
      "[0.025": "-0.386",
      "0.975]": "0.359"
    },
    {
      "name": "condition[T.d]",
      "Coef.": "0.227",
      "Std.Err.": "0.186",
      "z": "1.221",
      "P>|z|": "0.222",
      "[0.025": "-0.137",
      "0.975]": "0.592"
    },
    {
      "name": "condition[T.e]",
      "Coef.": "-0.100",
      "Std.Err.": "0.187",
      "z": "-0.536",
      "P>|z|": "0.592",
      "[0.025": "-0.467",
      "0.975]": "0.267"
    },
    {
      "name": "snr",
      "Coef.": "-0.252",
      "Std.Err.": "0.038",
      "z": "-6.651",
      "P>|z|": "0.000",
      "[0.025": "-0.326",
      "0.975]": "-0.178"
    },
    {
      "name": "Group Var",
      "Coef.": "0.815",
      "Std.Err.": "0.458",
      "z": "",
      "P>|z|": "",
      "[0.025": "",
      "0.975]": ""
    }
  ],
  "aic": 308.3020639177216,
  "bic": 330.601997859978,
  "converged": true,
  "reference_condition": "a"
}