{
  "summary": [
    {
      "name": "Intercept",
      "Coef.": "109.741",
      "Std.Err.": "1.120",
      "z": "97.960",
      "P>|z|": "0.000",
      "[0.025": "107.545",
      "0.975]": "111.937"
    },
    {
      "name": "condition[T.Decrease by 2 (no 1)]",
      "Coef.": "0.664",
      "Std.Err.": "0.925",
      "z": "0.718",
      "P>|z|": "0.473",
      "[0.025": "-1.149",
      "0.975]": "2.478"
    },
    {
      "name": "condition[T.Decrease by 3 (no 1)]",
      "Coef.": "0.109",
      "Std.Err.": "0.979",
      "z": "0.111",
      "P>|z|": "0.911",
      "[0.025": "-1.810",
      "0.975]": "2.028"
    },
    {
      "name": "snr",
      "Coef.": "0.061",
      "Std.Err.": "0.139",
      "z": "0.438",
      "P>|z|": "0.661",
      "[0.025": "-0.211",
      "0.975]": "0.333"
    },
    {
      "name": "Group Var",
      "Coef.": "7.748",
      "Std.Err.": "2.493",
      "z": "",
      "P>|z|": "",
      "[0.025": "",
      "0.975]": ""
    }
  ],
  "aic": 228.85806942855126,
  "bic": 239.42527012271265,
  "converged": true,
  "reference_condition": "Decrease by 1 (no 1)"
}