{
  "summary": [
    {
      "name": "Intercept",
      "Coef.": "-7.581",
      "Std.Err.": "0.896",
      "z": "-8.458",
      "P>|z|": "0.000",
      "[0.025": "-9.337",
      "0.975]": "-5.824"
    },
    {
      "name": "condition[T.2b]",
      "Coef.": "1.698",
      "Std.Err.": "1.005",
      "z": "1.690",
      "P>|z|": "0.091",
      "[0.025": "-0.271",
      "0.975]": "3.667"
    },
    {
      "name": "condition[T.2c]",
      "Coef.": "2.867",
      "Std.Err.": "1.025",
      "z": "2.796",
      "P>|z|": "0.005",
      "[0.025": "0.857",
      "0.975]": "4.877"
    },
    {
      "name": "condition[T.2d]",
      "Coef.": "3.113",
      "Std.Err.": "0.996",
      "z": "3.124",
      "P>|z|": "0.002",
      "[0.025": "1.160",
      "0.975]": "5.066"
    },
    {
      "name": "snr",
      "Coef.": "-1.030",
      "Std.Err.": "0.195",
      "z": "-5.288",
      "P>|z|": "0.000",
      "[0.025": "-1.412",
      "0.975]": "-0.648"
    },
    {
      "name": "Group Var",
      "Coef.": "2.720",
      "Std.Err.": "0.764",
      "z": "",
      "P>|z|": "",
      "[0.025": "",
      "0.975]": ""
    }
  ],
  "aic": 352.975351922057,
  "bic": 368.40820025779374,
  "converged": true,
  "reference_condition": "2a"
}