{
  "summary": [
    {
      "name": "Intercept",
      "Coef.": "483.848",
      "Std.Err.": "7.702",
      "z": "62.820",
      "P>|z|": "0.000",
      "[0.025": "468.753",
      "0.975]": "498.944"
    },
    {
      "name": "condition[T.Decreasing Large]",
      "Coef.": "10.954",
      "Std.Err.": "6.923",
      "z": "1.582",
      "P>|z|": "0.114",
      "[0.025": "-2.614",
      "0.975]": "24.522"
    },
    {
      "name": "condition[T.Decreasing Small]",
      "Coef.": "2.219",
      "Std.Err.": "6.415",
      "z": "0.346",
      "P>|z|": "0.729",
      "[0.025": "-10.354",
      "0.975]": "14.792"
    },
    {
      "name": "snr",
      "Coef.": "-0.126",
      "Std.Err.": "0.493",
      "z": "-0.256",
      "P>|z|": "0.798",
      "[0.025": "-1.093",
      "0.975]": "0.840"
    },
    {
      "name": "Group Var",
      "Coef.": "362.498",
      "Std.Err.": "9.545",
      "z": "",
      "P>|z|": "",
      "[0.025": "",
      "0.975]": ""
    }
  ],
  "aic": 567.4589511645329,
  "bic": 580.0250185378654,
  "converged": true,
  "reference_condition": "Decreasing Crossover"
}