{
  "summary": [
    {
      "name": "Intercept",
      "Coef.": "-0.156",
      "Std.Err.": "0.277",
      "z": "-0.562",
      "P>|z|": "0.574",
      "[0.025": "-0.698",
      "0.975]": "0.387"
    },
    {
      "name": "condition[T.Increase by 2 (no 1)]",
      "Coef.": "0.053",
      "Std.Err.": "0.293",
      "z": "0.179",
      "P>|z|": "0.858",
      "[0.025": "-0.522",
      "0.975]": "0.627"
    },
    {
      "name": "condition[T.Increase by 3 (no 1)]",
      "Coef.": "0.445",
      "Std.Err.": "0.303",
      "z": "1.470",
      "P>|z|": "0.142",
      "[0.025": "-0.148",
      "0.975]": "1.038"
    },
    {
      "name": "snr",
      "Coef.": "0.724",
      "Std.Err.": "0.092",
      "z": "7.863",
      "P>|z|": "0.000",
      "[0.025": "0.544",
      "0.975]": "0.905"
    },
    {
      "name": "Group Var",
      "Coef.": "0.061",
      "Std.Err.": "0.174",
      "z": "",
      "P>|z|": "",
      "[0.025": "",
      "0.975]": ""
    }
  ],
  "aic": 120.69238667677729,
  "bic": 131.39752448028685,
  "converged": true,
  "reference_condition": "Increase by 1 (no 1)"
}