{
  "summary": [
    {
      "Coef.": "4.484",
      "Std.Err.": "0.846",
      "z": "5.300",
      "P>|z|": "0.000",
      "[0.025": "2.826",
      "0.975]": "6.143"
    },
    {
      "Coef.": "-3.256",
      "Std.Err.": "0.282",
      "z": "-11.543",
      "P>|z|": "0.000",
      "[0.025": "-3.809",
      "0.975]": "-2.703"
    },
    {
      "Coef.": "0.875",
      "Std.Err.": "",
      "z": "",
      "P>|z|": "",
      "[0.025": "",
      "0.975]": ""
    }
  ],
  "aic": 18.192708074009623,
  "bic": 14.587157228682063,
  "converged": true
}