{
  "summary": [
    {
      "name": "Intercept",
      "Coef.": "0.850",
      "Std.Err.": "0.337",
      "z": "2.526",
      "P>|z|": "0.012",
      "[0.025": "0.190",
      "0.975]": "1.510"
    },
    {
      "name": "condition[T.Increasing (any step)]",
      "Coef.": "-0.353",
      "Std.Err.": "0.193",
      "z": "-1.827",
      "P>|z|": "0.068",
      "[0.025": "-0.731",
      "0.975]": "0.026"
    },
    {
      "name": "condition[T.No Change]",
      "Coef.": "-0.048",
      "Std.Err.": "0.194",
      "z": "-0.250",
      "P>|z|": "0.803",
      "[0.025": "-0.429",
      "0.975]": "0.332"
    },
    {
      "name": "snr",
      "Coef.": "0.124",
      "Std.Err.": "0.026",
      "z": "4.684",
      "P>|z|": "0.000",
      "[0.025": "0.072",
      "0.975]": "0.176"
    },
    {
      "name": "Group Var",
      "Coef.": "1.868",
      "Std.Err.": "1.103",
      "z": "",
      "P>|z|": "",
      "[0.025": "",
      "0.975]": ""
    }
  ],
  "aic": 220.68487776295905,
  "bic": 234.34487447705538,
  "converged": true,
  "reference_condition": "Decreasing (any step)"
}