{
  "summary": [
    {
      "name": "Intercept",
      "Coef.": "177.397",
      "Std.Err.": "4.577",
      "z": "38.760",
      "P>|z|": "0.000",
      "[0.025": "168.427",
      "0.975]": "186.367"
    },
    {
      "name": "condition[T.Increasing (any step)]",
      "Coef.": "-5.990",
      "Std.Err.": "2.639",
      "z": "-2.270",
      "P>|z|": "0.023",
      "[0.025": "-11.161",
      "0.975]": "-0.818"
    },
    {
      "name": "condition[T.No Change]",
      "Coef.": "-1.626",
      "Std.Err.": "3.124",
      "z": "-0.520",
      "P>|z|": "0.603",
      "[0.025": "-7.749",
      "0.975]": "4.498"
    },
    {
      "name": "snr",
      "Coef.": "-0.017",
      "Std.Err.": "0.224",
      "z": "-0.075",
      "P>|z|": "0.940",
      "[0.025": "-0.455",
      "0.975]": "0.421"
    },
    {
      "name": "Group Var",
      "Coef.": "191.963",
      "Std.Err.": "8.779",
      "z": "",
      "P>|z|": "",
      "[0.025": "",
      "0.975]": ""
    }
  ],
  "aic": 584.4005834965774,
  "bic": 598.0605802106737,
  "converged": true,
  "reference_condition": "Decreasing (any step)"
}