{
  "summary": [
    {
      "name": "Intercept",
      "Coef.": "3.135",
      "Std.Err.": "0.636",
      "z": "4.925",
      "P>|z|": "0.000",
      "[0.025": "1.887",
      "0.975]": "4.382"
    },
    {
      "name": "condition[T.Increasing Large]",
      "Coef.": "1.369",
      "Std.Err.": "0.444",
      "z": "3.080",
      "P>|z|": "0.002",
      "[0.025": "0.498",
      "0.975]": "2.240"
    },
    {
      "name": "condition[T.Increasing Small]",
      "Coef.": "0.435",
      "Std.Err.": "0.375",
      "z": "1.161",
      "P>|z|": "0.246",
      "[0.025": "-0.299",
      "0.975]": "1.169"
    },
    {
      "name": "snr",
      "Coef.": "0.151",
      "Std.Err.": "0.053",
      "z": "2.824",
      "P>|z|": "0.005",
      "[0.025": "0.046",
      "0.975]": "0.255"
    },
    {
      "name": "Group Var",
      "Coef.": "3.956",
      "Std.Err.": "1.790",
      "z": "",
      "P>|z|": "",
      "[0.025": "",
      "0.975]": ""
    }
  ],
  "aic": 224.299906933211,
  "bic": 236.23381121259663,
  "converged": true,
  "reference_condition": "Increasing Crossover"
}