{
  "summary": [
    {
      "name": "Intercept",
      "Coef.": "97.016",
      "Std.Err.": "2.316",
      "z": "41.882",
      "P>|z|": "0.000",
      "[0.025": "92.476",
      "0.975]": "101.556"
    },
    {
      "name": "condition[T.45 Incorrect]",
      "Coef.": "5.924",
      "Std.Err.": "2.880",
      "z": "2.057",
      "P>|z|": "0.040",
      "[0.025": "0.279",
      "0.975]": "11.569"
    },
    {
      "name": "snr",
      "Coef.": "0.322",
      "Std.Err.": "0.510",
      "z": "0.632",
      "P>|z|": "0.527",
      "[0.025": "-0.677",
      "0.975]": "1.322"
    },
    {
      "name": "Group Var",
      "Coef.": "39.030",
      "Std.Err.": "6.974",
      "z": "",
      "P>|z|": "",
      "[0.025": "",
      "0.975]": ""
    }
  ],
  "aic": 186.06559050905827,
  "bic": 192.15996963339927,
  "converged": true,
  "reference_condition": "45 Correct"
}