{
  "summary": [
    {
      "name": "Intercept",
      "Coef.": "-4.467",
      "Std.Err.": "0.504",
      "z": "-8.857",
      "P>|z|": "0.000",
      "[0.025": "-5.455",
      "0.975]": "-3.478"
    },
    {
      "name": "condition[T.2 to 3]",
      "Coef.": "0.760",
      "Std.Err.": "0.513",
      "z": "1.484",
      "P>|z|": "0.138",
      "[0.025": "-0.244",
      "0.975]": "1.765"
    },
    {
      "name": "condition[T.3 to 3]",
      "Coef.": "0.479",
      "Std.Err.": "0.516",
      "z": "0.928",
      "P>|z|": "0.354",
      "[0.025": "-0.533",
      "0.975]": "1.490"
    },
    {
      "name": "condition[T.4 to 3]",
      "Coef.": "0.065",
      "Std.Err.": "0.507",
      "z": "0.127",
      "P>|z|": "0.899",
      "[0.025": "-0.929",
      "0.975]": "1.058"
    },
    {
      "name": "condition[T.5 to 3]",
      "Coef.": "0.015",
      "Std.Err.": "0.508",
      "z": "0.030",
      "P>|z|": "0.976",
      "[0.025": "-0.980",
      "0.975]": "1.011"
    },
    {
      "name": "condition[T.6 to 3]",
      "Coef.": "-0.280",
      "Std.Err.": "0.506",
      "z": "-0.553",
      "P>|z|": "0.580",
      "[0.025": "-1.272",
      "0.975]": "0.712"
    },
    {
      "name": "snr",
      "Coef.": "-0.423",
      "Std.Err.": "0.064",
      "z": "-6.649",
      "P>|z|": "0.000",
      "[0.025": "-0.548",
      "0.975]": "-0.298"
    },
    {
      "name": "Group Var",
      "Coef.": "1.148",
      "Std.Err.": "0.305",
      "z": "",
      "P>|z|": "",
      "[0.025": "",
      "0.975]": ""
    }
  ],
  "aic": 616.6379091503464,
  "bic": 643.3662288465305,
  "converged": true,
  "reference_condition": "1 to 3"
}