{
  "timestamp": "2025-10-17 03:15:05",
  "analysis_id": "tables",
  "config_file": "C:\\Users\\yurig\\AppData\\Local\\Temp\\stats_landing_on_3_any_preceding_ACC1_91zg5c7d.yaml",
  "input_csv": "D:\\eeg-image-analysis-v2\\docs\\assets\\tables\\landing_on_3_any_preceding_ACC1\\subject_measurements.csv",
  "components_tested": [
    "N1",
    "P1",
    "P3b"
  ],
  "dependent_variables": [
    "mean_amplitude_roi",
    "latency_frac_area_ms"
  ],
  "library_versions": {
    "pingouin": "0.5.5",
    "statsmodels": "0.14.5",
    "mne": "1.10.1",
    "scipy": "1.16.2",
    "pandas": "2.3.1",
    "numpy": "2.3.3",
    "python": "3.12.11"
  },
  "analysis_settings": {
    "measurement_window_method": "collapsed_localizer_fwhm",
    "fal_fraction": 0.5,
    "latency_measure": "fal_50",
    "amplitude_measure": "mean",
    "filters": {
      "min_snr": null,
      "dropna": true
    },
    "baseline_period_ms": "[-100, 0]"
  },
  "correction_family": "component",
  "missing_data_policy": "ANOVA and pairwise tests were run on complete cases. Subject-condition combinations with missing latency values or below-threshold SNR were excluded listwise. Linear mixed-effects models retained all subjects with valid measurements to optimally handle missing data.",
  "data_summary": {
    "n_total_measurements": 360,
    "n_subjects": 24,
    "n_conditions": 5
  },
  "tests_run": {
    "anova": true,
    "pairwise": true,
    "lmm": true,
    "descriptives": true
  },
  "results": {
    "anova": {
      "N1_mean_amplitude_roi": {
        "component": "N1",
        "dv": "mean_amplitude_roi",
        "test": "ANOVA",
        "F": 2.2939003605648534,
        "p_unc": 0.06698250980256043,
        "output_file": "anova_N1_mean_amplitude_roi.csv",
        "epsilon": 0.7797067105902659,
        "effect_size_ng2": 0.05889310837972056
      },
      "N1_latency_frac_area_ms": {
        "component": "N1",
        "dv": "latency_frac_area_ms",
        "test": "ANOVA",
        "F": 0.6711218653211747,
        "p_unc": 0.6140263084541977,
        "output_file": "anova_N1_latency_frac_area_ms.csv",
        "epsilon": 0.6814063120774693,
        "effect_size_ng2": 0.00954054911438032
      },
      "P1_mean_amplitude_roi": {
        "component": "P1",
        "dv": "mean_amplitude_roi",
        "test": "ANOVA",
        "F": 0.6738317688470248,
        "p_unc": 0.6197461552696688,
        "output_file": "anova_P1_mean_amplitude_roi.csv",
        "epsilon": 0.38898132056357676,
        "effect_size_ng2": 0.09601771898005061
      },
      "P1_latency_frac_area_ms": {
        "component": "P1",
        "dv": "latency_frac_area_ms",
        "test": "ANOVA",
        "F": 0.21640573466436314,
        "p_unc": 0.9254306818709641,
        "output_file": "anova_P1_latency_frac_area_ms.csv",
        "epsilon": 0.5545828464816271,
        "effect_size_ng2": 0.034582792381391454
      },
      "P3b_mean_amplitude_roi": {
        "component": "P3b",
        "dv": "mean_amplitude_roi",
        "test": "ANOVA",
        "F": 1.5032361379153039,
        "p_unc": 0.21365477108153097,
        "output_file": "anova_P3b_mean_amplitude_roi.csv",
        "epsilon": 0.6852349254349678,
        "effect_size_ng2": 0.0329613737060418
      },
      "P3b_latency_frac_area_ms": {
        "component": "P3b",
        "dv": "latency_frac_area_ms",
        "test": "ANOVA",
        "F": 0.5002816842651514,
        "p_unc": 0.7355930054712004,
        "output_file": "anova_P3b_latency_frac_area_ms.csv",
        "epsilon": 0.7197339184314839,
        "effect_size_ng2": 0.017180537734039672
      }
    },
    "pairwise": {
      "N1_mean_amplitude_roi": {
        "component": "N1",
        "dv": "mean_amplitude_roi",
        "test": "Pairwise",
        "n_comparisons": 10,
        "n_significant": 0,
        "correction": "fdr_bh",
        "output_file": "pairwise_N1_mean_amplitude_roi.csv"
      },
      "N1_latency_frac_area_ms": {
        "component": "N1",
        "dv": "latency_frac_area_ms",
        "test": "Pairwise",
        "n_comparisons": 10,
        "n_significant": 0,
        "correction": "fdr_bh",
        "output_file": "pairwise_N1_latency_frac_area_ms.csv"
      },
      "P1_mean_amplitude_roi": {
        "component": "P1",
        "dv": "mean_amplitude_roi",
        "test": "Pairwise",
        "n_comparisons": 10,
        "n_significant": 0,
        "correction": "fdr_bh",
        "output_file": "pairwise_P1_mean_amplitude_roi.csv"
      },
      "P1_latency_frac_area_ms": {
        "component": "P1",
        "dv": "latency_frac_area_ms",
        "test": "Pairwise",
        "n_comparisons": 10,
        "n_significant": 0,
        "correction": "fdr_bh",
        "output_file": "pairwise_P1_latency_frac_area_ms.csv"
      },
      "P3b_mean_amplitude_roi": {
        "component": "P3b",
        "dv": "mean_amplitude_roi",
        "test": "Pairwise",
        "n_comparisons": 10,
        "n_significant": 0,
        "correction": "fdr_bh",
        "output_file": "pairwise_P3b_mean_amplitude_roi.csv"
      },
      "P3b_latency_frac_area_ms": {
        "component": "P3b",
        "dv": "latency_frac_area_ms",
        "test": "Pairwise",
        "n_comparisons": 10,
        "n_significant": 0,
        "correction": "fdr_bh",
        "output_file": "pairwise_P3b_latency_frac_area_ms.csv"
      }
    },
    "lmm": {
      "N1_mean_amplitude_roi": {
        "component": "N1",
        "dv": "mean_amplitude_roi",
        "test": "LMM",
        "aic": 407.81845730282953,
        "bic": 429.77791432973555,
        "converged": true,
        "output_file": "lmm_N1_mean_amplitude_roi.json"
      },
      "N1_latency_frac_area_ms": {
        "component": "N1",
        "dv": "latency_frac_area_ms",
        "test": "LMM",
        "aic": 831.4973720306043,
        "bic": 853.4568290575103,
        "converged": true,
        "output_file": "lmm_N1_latency_frac_area_ms.json"
      },
      "P1_mean_amplitude_roi": {
        "component": "P1",
        "dv": "mean_amplitude_roi",
        "test": "LMM",
        "aic": 212.27936120566068,
        "bic": 230.26732314205555,
        "converged": true,
        "output_file": "lmm_P1_mean_amplitude_roi.json"
      },
      "P1_latency_frac_area_ms": {
        "component": "P1",
        "dv": "latency_frac_area_ms",
        "test": "LMM",
        "aic": 427.75425279576984,
        "bic": 445.7422147321647,
        "converged": true,
        "output_file": "lmm_P1_latency_frac_area_ms.json"
      },
      "P3b_mean_amplitude_roi": {
        "component": "P3b",
        "dv": "mean_amplitude_roi",
        "test": "LMM",
        "aic": 384.61542228010666,
        "bic": 405.04643741291096,
        "converged": true,
        "output_file": "lmm_P3b_mean_amplitude_roi.json"
      },
      "P3b_latency_frac_area_ms": {
        "component": "P3b",
        "dv": "latency_frac_area_ms",
        "test": "LMM",
        "aic": 834.9917351635097,
        "bic": 855.422750296314,
        "converged": true,
        "output_file": "lmm_P3b_latency_frac_area_ms.json"
      }
    }
  }
}