{
  "summary": [
    {
      "name": "Intercept",
      "Coef.": "493.532",
      "Std.Err.": "7.931",
      "z": "62.225",
      "P>|z|": "0.000",
      "[0.025": "477.987",
      "0.975]": "509.078"
    },
    {
      "name": "condition[T.4 to 2]",
      "Coef.": "-12.218",
      "Std.Err.": "8.975",
      "z": "-1.361",
      "P>|z|": "0.173",
      "[0.025": "-29.808",
      "0.975]": "5.372"
    },
    {
      "name": "condition[T.4 to 3]",
      "Coef.": "-13.308",
      "Std.Err.": "8.851",
      "z": "-1.504",
      "P>|z|": "0.133",
      "[0.025": "-30.655",
      "0.975]": "4.040"
    },
    {
      "name": "condition[T.4 to 4]",
      "Coef.": "-17.566",
      "Std.Err.": "8.998",
      "z": "-1.952",
      "P>|z|": "0.051",
      "[0.025": "-35.201",
      "0.975]": "0.069"
    },
    {
      "name": "condition[T.4 to 5]",
      "Coef.": "1.145",
      "Std.Err.": "8.898",
      "z": "0.129",
      "P>|z|": "0.898",
      "[0.025": "-16.294",
      "0.975]": "18.584"
    },
    {
      "name": "condition[T.4 to 6]",
      "Coef.": "5.282",
      "Std.Err.": "8.870",
      "z": "0.595",
      "P>|z|": "0.552",
      "[0.025": "-12.103",
      "0.975]": "22.668"
    },
    {
      "name": "snr",
      "Coef.": "-1.071",
      "Std.Err.": "0.647",
      "z": "-1.657",
      "P>|z|": "0.098",
      "[0.025": "-2.339",
      "0.975]": "0.196"
    },
    {
      "name": "Group Var",
      "Coef.": "248.055",
      "Std.Err.": "4.190",
      "z": "",
      "P>|z|": "",
      "[0.025": "",
      "0.975]": ""
    }
  ],
  "aic": 1433.272368883568,
  "bic": 1460.000688579752,
  "converged": true,
  "reference_condition": "4 to 1"
}