{
  "summary": [
    {
      "name": "Intercept",
      "Coef.": "101.249",
      "Std.Err.": "3.426",
      "z": "29.553",
      "P>|z|": "0.000",
      "[0.025": "94.534",
      "0.975]": "107.963"
    },
    {
      "name": "condition[T.5b3]",
      "Coef.": "-11.720",
      "Std.Err.": "5.241",
      "z": "-2.236",
      "P>|z|": "0.025",
      "[0.025": "-21.992",
      "0.975]": "-1.447"
    },
    {
      "name": "condition[T.5c3]",
      "Coef.": "-2.542",
      "Std.Err.": "4.407",
      "z": "-0.577",
      "P>|z|": "0.564",
      "[0.025": "-11.180",
      "0.975]": "6.095"
    },
    {
      "name": "condition[T.5d3]",
      "Coef.": "1.007",
      "Std.Err.": "5.289",
      "z": "0.190",
      "P>|z|": "0.849",
      "[0.025": "-9.359",
      "0.975]": "11.373"
    },
    {
      "name": "condition[T.5e3]",
      "Coef.": "-6.414",
      "Std.Err.": "5.247",
      "z": "-1.222",
      "P>|z|": "0.222",
      "[0.025": "-16.699",
      "0.975]": "3.870"
    },
    {
      "name": "snr",
      "Coef.": "1.553",
      "Std.Err.": "1.206",
      "z": "1.288",
      "P>|z|": "0.198",
      "[0.025": "-0.810",
      "0.975]": "3.917"
    },
    {
      "name": "Group Var",
      "Coef.": "0.000",
      "Std.Err.": "1.967",
      "z": "",
      "P>|z|": "",
      "[0.025": "",
      "0.975]": ""
    }
  ],
  "aic": 508.6135381390063,
  "bic": 525.6306132193671,
  "converged": true,
  "reference_condition": "5a3"
}