{
  "summary": [
    {
      "name": "Intercept",
      "Coef.": "2.913",
      "Std.Err.": "0.540",
      "z": "5.395",
      "P>|z|": "0.000",
      "[0.025": "1.855",
      "0.975]": "3.972"
    },
    {
      "name": "condition[T.4 to 6]",
      "Coef.": "0.411",
      "Std.Err.": "0.463",
      "z": "0.889",
      "P>|z|": "0.374",
      "[0.025": "-0.496",
      "0.975]": "1.318"
    },
    {
      "name": "condition[T.5 to 6]",
      "Coef.": "2.944",
      "Std.Err.": "0.569",
      "z": "5.177",
      "P>|z|": "0.000",
      "[0.025": "1.829",
      "0.975]": "4.058"
    },
    {
      "name": "condition[T.6 to 6]",
      "Coef.": "-0.127",
      "Std.Err.": "0.479",
      "z": "-0.265",
      "P>|z|": "0.791",
      "[0.025": "-1.065",
      "0.975]": "0.811"
    },
    {
      "name": "snr",
      "Coef.": "0.635",
      "Std.Err.": "0.100",
      "z": "6.334",
      "P>|z|": "0.000",
      "[0.025": "0.439",
      "0.975]": "0.832"
    },
    {
      "name": "Group Var",
      "Coef.": "3.103",
      "Std.Err.": "1.098",
      "z": "",
      "P>|z|": "",
      "[0.025": "",
      "0.975]": ""
    }
  ],
  "aic": 256.5258304672607,
  "bic": 271.3019475164739,
  "converged": true,
  "reference_condition": "3 to 6"
}