{
  "summary": [
    {
      "name": "Intercept",
      "Coef.": "-2.231",
      "Std.Err.": "0.489",
      "z": "-4.561",
      "P>|z|": "0.000",
      "[0.025": "-3.190",
      "0.975]": "-1.272"
    },
    {
      "name": "condition[T.2 to 5]",
      "Coef.": "0.364",
      "Std.Err.": "0.366",
      "z": "0.994",
      "P>|z|": "0.320",
      "[0.025": "-0.353",
      "0.975]": "1.081"
    },
    {
      "name": "condition[T.3 to 6]",
      "Coef.": "-0.141",
      "Std.Err.": "0.367",
      "z": "-0.384",
      "P>|z|": "0.701",
      "[0.025": "-0.861",
      "0.975]": "0.579"
    },
    {
      "name": "snr",
      "Coef.": "-0.442",
      "Std.Err.": "0.084",
      "z": "-5.268",
      "P>|z|": "0.000",
      "[0.025": "-0.606",
      "0.975]": "-0.278"
    },
    {
      "name": "Group Var",
      "Coef.": "1.372",
      "Std.Err.": "0.591",
      "z": "",
      "P>|z|": "",
      "[0.025": "",
      "0.975]": ""
    }
  ],
  "aic": 260.901795515407,
  "bic": 274.2188417464636,
  "converged": true,
  "reference_condition": "1 to 4"
}